<?xml version="1.0" encoding="UTF-8" standalone="no"?>
<debugInfo>
<manifest filename="C:\SudarsanSRINIVASAN\dev\thirdface\manifest.xml"/>
<pcToLineNum>
<entry filename="C:\\SudarsanSRINIVASAN\\dev\\thirdface\\source\\thirdfaceApp.mc" id="1" lineNum="26" parent="globals" pc="268435457" symbol="getApp"/>
<entry filename="C:\\SudarsanSRINIVASAN\\dev\\thirdface\\source\\thirdfaceApp.mc" id="1" lineNum="27" parent="globals" pc="268435467" symbol="getApp"/>
<entry filename="C:\\SudarsanSRINIVASAN\\dev\\thirdface\\source\\thirdfaceApp.mc" id="2" lineNum="5" parent="globals/thirdfaceApp" pc="268435483" symbol="&lt;init&gt;"/>
<entry filename="C:\\SudarsanSRINIVASAN\\dev\\thirdface\\source\\thirdfaceApp.mc" id="4" lineNum="20" parent="globals/thirdfaceApp" pc="268435502" symbol="getInitialView"/>
<entry filename="C:\\SudarsanSRINIVASAN\\dev\\thirdface\\source\\thirdfaceApp.mc" id="4" lineNum="21" parent="globals/thirdfaceApp" pc="268435504" symbol="getInitialView"/>
<entry filename="C:\\SudarsanSRINIVASAN\\dev\\thirdface\\source\\thirdfaceApp.mc" id="5" lineNum="7" parent="globals/thirdfaceApp" pc="268435579" symbol="initialize"/>
<entry filename="C:\\SudarsanSRINIVASAN\\dev\\thirdface\\source\\thirdfaceApp.mc" id="5" lineNum="8" parent="globals/thirdfaceApp" pc="268435581" symbol="initialize"/>
<entry filename="C:\\SudarsanSRINIVASAN\\dev\\thirdface\\source\\thirdfaceView.mc" id="7" lineNum="7" parent="globals/thirdFaceDelegate" pc="268435600" symbol="&lt;init&gt;"/>
<entry filename="C:\\SudarsanSRINIVASAN\\dev\\thirdface\\source\\thirdfaceView.mc" id="8" lineNum="13" parent="globals/thirdFaceDelegate" pc="268435619" symbol="onPress"/>
<entry filename="C:\\SudarsanSRINIVASAN\\dev\\thirdface\\source\\thirdfaceView.mc" id="8" lineNum="14" parent="globals/thirdFaceDelegate" pc="268435623" symbol="onPress"/>
<entry filename="C:\\SudarsanSRINIVASAN\\dev\\thirdface\\source\\thirdfaceView.mc" id="8" lineNum="15" parent="globals/thirdFaceDelegate" pc="268435636" symbol="onPress"/>
<entry filename="C:\\SudarsanSRINIVASAN\\dev\\thirdface\\source\\thirdfaceView.mc" id="8" lineNum="16" parent="globals/thirdFaceDelegate" pc="268435646" symbol="onPress"/>
<entry filename="C:\\SudarsanSRINIVASAN\\dev\\thirdface\\source\\thirdfaceView.mc" id="8" lineNum="17" parent="globals/thirdFaceDelegate" pc="268435656" symbol="onPress"/>
<entry filename="C:\\SudarsanSRINIVASAN\\dev\\thirdface\\source\\thirdfaceView.mc" id="8" lineNum="18" parent="globals/thirdFaceDelegate" pc="268435660" symbol="onPress"/>
<entry filename="C:\\SudarsanSRINIVASAN\\dev\\thirdface\\source\\thirdfaceView.mc" id="8" lineNum="19" parent="globals/thirdFaceDelegate" pc="268435681" symbol="onPress"/>
<entry filename="C:\\SudarsanSRINIVASAN\\dev\\thirdface\\source\\thirdfaceView.mc" id="8" lineNum="20" parent="globals/thirdFaceDelegate" pc="268435717" symbol="onPress"/>
<entry filename="C:\\SudarsanSRINIVASAN\\dev\\thirdface\\source\\thirdfaceView.mc" id="8" lineNum="21" parent="globals/thirdFaceDelegate" pc="268435717" symbol="onPress"/>
<entry filename="C:\\SudarsanSRINIVASAN\\dev\\thirdface\\source\\thirdfaceView.mc" id="8" lineNum="22" parent="globals/thirdFaceDelegate" pc="268435770" symbol="onPress"/>
<entry filename="C:\\SudarsanSRINIVASAN\\dev\\thirdface\\source\\thirdfaceView.mc" id="8" lineNum="23" parent="globals/thirdFaceDelegate" pc="268435791" symbol="onPress"/>
<entry filename="C:\\SudarsanSRINIVASAN\\dev\\thirdface\\source\\thirdfaceView.mc" id="8" lineNum="24" parent="globals/thirdFaceDelegate" pc="268435826" symbol="onPress"/>
<entry filename="C:\\SudarsanSRINIVASAN\\dev\\thirdface\\source\\thirdfaceView.mc" id="8" lineNum="25" parent="globals/thirdFaceDelegate" pc="268435849" symbol="onPress"/>
<entry filename="C:\\SudarsanSRINIVASAN\\dev\\thirdface\\source\\thirdfaceView.mc" id="8" lineNum="26" parent="globals/thirdFaceDelegate" pc="268435902" symbol="onPress"/>
<entry filename="C:\\SudarsanSRINIVASAN\\dev\\thirdface\\source\\thirdfaceView.mc" id="8" lineNum="27" parent="globals/thirdFaceDelegate" pc="268435923" symbol="onPress"/>
<entry filename="C:\\SudarsanSRINIVASAN\\dev\\thirdface\\source\\thirdfaceView.mc" id="8" lineNum="28" parent="globals/thirdFaceDelegate" pc="268435958" symbol="onPress"/>
<entry filename="C:\\SudarsanSRINIVASAN\\dev\\thirdface\\source\\thirdfaceView.mc" id="8" lineNum="29" parent="globals/thirdFaceDelegate" pc="268435981" symbol="onPress"/>
<entry filename="C:\\SudarsanSRINIVASAN\\dev\\thirdface\\source\\thirdfaceView.mc" id="8" lineNum="30" parent="globals/thirdFaceDelegate" pc="268436034" symbol="onPress"/>
<entry filename="C:\\SudarsanSRINIVASAN\\dev\\thirdface\\source\\thirdfaceView.mc" id="8" lineNum="31" parent="globals/thirdFaceDelegate" pc="268436055" symbol="onPress"/>
<entry filename="C:\\SudarsanSRINIVASAN\\dev\\thirdface\\source\\thirdfaceView.mc" id="8" lineNum="32" parent="globals/thirdFaceDelegate" pc="268436090" symbol="onPress"/>
<entry filename="C:\\SudarsanSRINIVASAN\\dev\\thirdface\\source\\thirdfaceView.mc" id="8" lineNum="33" parent="globals/thirdFaceDelegate" pc="268436113" symbol="onPress"/>
<entry filename="C:\\SudarsanSRINIVASAN\\dev\\thirdface\\source\\thirdfaceView.mc" id="8" lineNum="34" parent="globals/thirdFaceDelegate" pc="268436166" symbol="onPress"/>
<entry filename="C:\\SudarsanSRINIVASAN\\dev\\thirdface\\source\\thirdfaceView.mc" id="8" lineNum="35" parent="globals/thirdFaceDelegate" pc="268436187" symbol="onPress"/>
<entry filename="C:\\SudarsanSRINIVASAN\\dev\\thirdface\\source\\thirdfaceView.mc" id="8" lineNum="36" parent="globals/thirdFaceDelegate" pc="268436222" symbol="onPress"/>
<entry filename="C:\\SudarsanSRINIVASAN\\dev\\thirdface\\source\\thirdfaceView.mc" id="8" lineNum="37" parent="globals/thirdFaceDelegate" pc="268436245" symbol="onPress"/>
<entry filename="C:\\SudarsanSRINIVASAN\\dev\\thirdface\\source\\thirdfaceView.mc" id="8" lineNum="38" parent="globals/thirdFaceDelegate" pc="268436298" symbol="onPress"/>
<entry filename="C:\\SudarsanSRINIVASAN\\dev\\thirdface\\source\\thirdfaceView.mc" id="8" lineNum="39" parent="globals/thirdFaceDelegate" pc="268436319" symbol="onPress"/>
<entry filename="C:\\SudarsanSRINIVASAN\\dev\\thirdface\\source\\thirdfaceView.mc" id="8" lineNum="40" parent="globals/thirdFaceDelegate" pc="268436354" symbol="onPress"/>
<entry filename="C:\\SudarsanSRINIVASAN\\dev\\thirdface\\source\\thirdfaceView.mc" id="8" lineNum="41" parent="globals/thirdFaceDelegate" pc="268436377" symbol="onPress"/>
<entry filename="C:\\SudarsanSRINIVASAN\\dev\\thirdface\\source\\thirdfaceView.mc" id="8" lineNum="42" parent="globals/thirdFaceDelegate" pc="268436430" symbol="onPress"/>
<entry filename="C:\\SudarsanSRINIVASAN\\dev\\thirdface\\source\\thirdfaceView.mc" id="8" lineNum="43" parent="globals/thirdFaceDelegate" pc="268436451" symbol="onPress"/>
<entry filename="C:\\SudarsanSRINIVASAN\\dev\\thirdface\\source\\thirdfaceView.mc" id="8" lineNum="44" parent="globals/thirdFaceDelegate" pc="268436486" symbol="onPress"/>
<entry filename="C:\\SudarsanSRINIVASAN\\dev\\thirdface\\source\\thirdfaceView.mc" id="8" lineNum="45" parent="globals/thirdFaceDelegate" pc="268436509" symbol="onPress"/>
<entry filename="C:\\SudarsanSRINIVASAN\\dev\\thirdface\\source\\thirdfaceView.mc" id="8" lineNum="46" parent="globals/thirdFaceDelegate" pc="268436562" symbol="onPress"/>
<entry filename="C:\\SudarsanSRINIVASAN\\dev\\thirdface\\source\\thirdfaceView.mc" id="8" lineNum="47" parent="globals/thirdFaceDelegate" pc="268436583" symbol="onPress"/>
<entry filename="C:\\SudarsanSRINIVASAN\\dev\\thirdface\\source\\thirdfaceView.mc" id="8" lineNum="48" parent="globals/thirdFaceDelegate" pc="268436618" symbol="onPress"/>
<entry filename="C:\\SudarsanSRINIVASAN\\dev\\thirdface\\source\\thirdfaceView.mc" id="8" lineNum="50" parent="globals/thirdFaceDelegate" pc="268436641" symbol="onPress"/>
<entry filename="C:\\SudarsanSRINIVASAN\\dev\\thirdface\\source\\thirdfaceView.mc" id="8" lineNum="52" parent="globals/thirdFaceDelegate" pc="268436668" symbol="onPress"/>
<entry filename="C:\\SudarsanSRINIVASAN\\dev\\thirdface\\source\\thirdfaceView.mc" id="8" lineNum="53" parent="globals/thirdFaceDelegate" pc="268436672" symbol="onPress"/>
<entry filename="C:\\SudarsanSRINIVASAN\\dev\\thirdface\\source\\thirdfaceView.mc" id="8" lineNum="56" parent="globals/thirdFaceDelegate" pc="268436705" symbol="onPress"/>
<entry filename="C:\\SudarsanSRINIVASAN\\dev\\thirdface\\source\\thirdfaceView.mc" id="9" lineNum="9" parent="globals/thirdFaceDelegate" pc="268436708" symbol="initialize"/>
<entry filename="C:\\SudarsanSRINIVASAN\\dev\\thirdface\\source\\thirdfaceView.mc" id="9" lineNum="10" parent="globals/thirdFaceDelegate" pc="268436710" symbol="initialize"/>
<entry filename="c:\\SudarsanSRINIVASAN\\dev\\thirdface\\side_load\\gen\\006-B3851-00\\source\\Rez.mcgen" id="10" lineNum="7" parent="globals/Rez" pc="268436729" symbol="&lt;init&gt;"/>
<entry filename="C:\\SudarsanSRINIVASAN\\dev\\thirdface\\source\\thirdfaceView.mc" id="11" lineNum="60" parent="globals/thirdfaceView" pc="268436753" symbol="&lt;init&gt;"/>
<entry filename="C:\\SudarsanSRINIVASAN\\dev\\thirdface\\source\\thirdfaceView.mc" id="12" lineNum="223" parent="globals/thirdfaceView" pc="268436772" symbol="getMoonAge"/>
<entry filename="C:\\SudarsanSRINIVASAN\\dev\\thirdface\\source\\thirdfaceView.mc" id="12" lineNum="224" parent="globals/thirdfaceView" pc="268436776" symbol="getMoonAge"/>
<entry filename="C:\\SudarsanSRINIVASAN\\dev\\thirdface\\source\\thirdfaceView.mc" id="12" lineNum="227" parent="globals/thirdfaceView" pc="268436795" symbol="getMoonAge"/>
<entry filename="C:\\SudarsanSRINIVASAN\\dev\\thirdface\\source\\thirdfaceView.mc" id="12" lineNum="225" parent="globals/thirdfaceView" pc="268436795" symbol="getMoonAge"/>
<entry filename="C:\\SudarsanSRINIVASAN\\dev\\thirdface\\source\\thirdfaceView.mc" id="12" lineNum="228" parent="globals/thirdfaceView" pc="268436811" symbol="getMoonAge"/>
<entry filename="C:\\SudarsanSRINIVASAN\\dev\\thirdface\\source\\thirdfaceView.mc" id="12" lineNum="231" parent="globals/thirdfaceView" pc="268436835" symbol="getMoonAge"/>
<entry filename="C:\\SudarsanSRINIVASAN\\dev\\thirdface\\source\\thirdfaceView.mc" id="12" lineNum="232" parent="globals/thirdfaceView" pc="268436846" symbol="getMoonAge"/>
<entry filename="C:\\SudarsanSRINIVASAN\\dev\\thirdface\\source\\thirdfaceView.mc" id="12" lineNum="234" parent="globals/thirdfaceView" pc="268436865" symbol="getMoonAge"/>
<entry filename="C:\\SudarsanSRINIVASAN\\dev\\thirdface\\source\\thirdfaceView.mc" id="12" lineNum="237" parent="globals/thirdfaceView" pc="268436881" symbol="getMoonAge"/>
<entry filename="C:\\SudarsanSRINIVASAN\\dev\\thirdface\\source\\thirdfaceView.mc" id="12" lineNum="238" parent="globals/thirdfaceView" pc="268436908" symbol="getMoonAge"/>
<entry filename="C:\\SudarsanSRINIVASAN\\dev\\thirdface\\source\\thirdfaceView.mc" id="13" lineNum="460" parent="globals/thirdfaceView" pc="268436911" symbol="getYFromAngle"/>
<entry filename="C:\\SudarsanSRINIVASAN\\dev\\thirdface\\source\\thirdfaceView.mc" id="13" lineNum="461" parent="globals/thirdfaceView" pc="268436915" symbol="getYFromAngle"/>
<entry filename="C:\\SudarsanSRINIVASAN\\dev\\thirdface\\source\\thirdfaceView.mc" id="13" lineNum="462" parent="globals/thirdfaceView" pc="268436951" symbol="getYFromAngle"/>
<entry filename="C:\\SudarsanSRINIVASAN\\dev\\thirdface\\source\\thirdfaceView.mc" id="14" lineNum="441" parent="globals/thirdfaceView" pc="268436954" symbol="drawProgressCCW"/>
<entry filename="C:\\SudarsanSRINIVASAN\\dev\\thirdface\\source\\thirdfaceView.mc" id="14" lineNum="442" parent="globals/thirdfaceView" pc="268436958" symbol="drawProgressCCW"/>
<entry filename="C:\\SudarsanSRINIVASAN\\dev\\thirdface\\source\\thirdfaceView.mc" id="14" lineNum="443" parent="globals/thirdfaceView" pc="268436974" symbol="drawProgressCCW"/>
<entry filename="C:\\SudarsanSRINIVASAN\\dev\\thirdface\\source\\thirdfaceView.mc" id="14" lineNum="444" parent="globals/thirdfaceView" pc="268436990" symbol="drawProgressCCW"/>
<entry filename="C:\\SudarsanSRINIVASAN\\dev\\thirdface\\source\\thirdfaceView.mc" id="14" lineNum="445" parent="globals/thirdfaceView" pc="268437004" symbol="drawProgressCCW"/>
<entry filename="C:\\SudarsanSRINIVASAN\\dev\\thirdface\\source\\thirdfaceView.mc" id="15" lineNum="449" parent="globals/thirdfaceView" pc="268437035" symbol="getAngleFromTime"/>
<entry filename="C:\\SudarsanSRINIVASAN\\dev\\thirdface\\source\\thirdfaceView.mc" id="15" lineNum="450" parent="globals/thirdfaceView" pc="268437037" symbol="getAngleFromTime"/>
<entry filename="C:\\SudarsanSRINIVASAN\\dev\\thirdface\\source\\thirdfaceView.mc" id="16" lineNum="241" parent="globals/thirdfaceView" pc="268437052" symbol="drawMoon"/>
<entry filename="C:\\SudarsanSRINIVASAN\\dev\\thirdface\\source\\thirdfaceView.mc" id="16" lineNum="242" parent="globals/thirdfaceView" pc="268437056" symbol="drawMoon"/>
<entry filename="C:\\SudarsanSRINIVASAN\\dev\\thirdface\\source\\thirdfaceView.mc" id="16" lineNum="247" parent="globals/thirdfaceView" pc="268437075" symbol="drawMoon"/>
<entry filename="C:\\SudarsanSRINIVASAN\\dev\\thirdface\\source\\thirdfaceView.mc" id="16" lineNum="243" parent="globals/thirdfaceView" pc="268437075" symbol="drawMoon"/>
<entry filename="C:\\SudarsanSRINIVASAN\\dev\\thirdface\\source\\thirdfaceView.mc" id="16" lineNum="248" parent="globals/thirdfaceView" pc="268437082" symbol="drawMoon"/>
<entry filename="C:\\SudarsanSRINIVASAN\\dev\\thirdface\\source\\thirdfaceView.mc" id="16" lineNum="250" parent="globals/thirdfaceView" pc="268437106" symbol="drawMoon"/>
<entry filename="C:\\SudarsanSRINIVASAN\\dev\\thirdface\\source\\thirdfaceView.mc" id="16" lineNum="251" parent="globals/thirdfaceView" pc="268437129" symbol="drawMoon"/>
<entry filename="C:\\SudarsanSRINIVASAN\\dev\\thirdface\\source\\thirdfaceView.mc" id="16" lineNum="252" parent="globals/thirdfaceView" pc="268437143" symbol="drawMoon"/>
<entry filename="C:\\SudarsanSRINIVASAN\\dev\\thirdface\\source\\thirdfaceView.mc" id="16" lineNum="253" parent="globals/thirdfaceView" pc="268437165" symbol="drawMoon"/>
<entry filename="C:\\SudarsanSRINIVASAN\\dev\\thirdface\\source\\thirdfaceView.mc" id="16" lineNum="254" parent="globals/thirdfaceView" pc="268437210" symbol="drawMoon"/>
<entry filename="C:\\SudarsanSRINIVASAN\\dev\\thirdface\\source\\thirdfaceView.mc" id="16" lineNum="255" parent="globals/thirdfaceView" pc="268437236" symbol="drawMoon"/>
<entry filename="C:\\SudarsanSRINIVASAN\\dev\\thirdface\\source\\thirdfaceView.mc" id="16" lineNum="256" parent="globals/thirdfaceView" pc="268437243" symbol="drawMoon"/>
<entry filename="C:\\SudarsanSRINIVASAN\\dev\\thirdface\\source\\thirdfaceView.mc" id="16" lineNum="257" parent="globals/thirdfaceView" pc="268437277" symbol="drawMoon"/>
<entry filename="C:\\SudarsanSRINIVASAN\\dev\\thirdface\\source\\thirdfaceView.mc" id="16" lineNum="258" parent="globals/thirdfaceView" pc="268437294" symbol="drawMoon"/>
<entry filename="C:\\SudarsanSRINIVASAN\\dev\\thirdface\\source\\thirdfaceView.mc" id="16" lineNum="259" parent="globals/thirdfaceView" pc="268437313" symbol="drawMoon"/>
<entry filename="C:\\SudarsanSRINIVASAN\\dev\\thirdface\\source\\thirdfaceView.mc" id="16" lineNum="260" parent="globals/thirdfaceView" pc="268437342" symbol="drawMoon"/>
<entry filename="C:\\SudarsanSRINIVASAN\\dev\\thirdface\\source\\thirdfaceView.mc" id="16" lineNum="261" parent="globals/thirdfaceView" pc="268437364" symbol="drawMoon"/>
<entry filename="C:\\SudarsanSRINIVASAN\\dev\\thirdface\\source\\thirdfaceView.mc" id="18" lineNum="433" parent="globals/thirdfaceView" pc="268437383" symbol="drawProgressCW"/>
<entry filename="C:\\SudarsanSRINIVASAN\\dev\\thirdface\\source\\thirdfaceView.mc" id="18" lineNum="434" parent="globals/thirdfaceView" pc="268437387" symbol="drawProgressCW"/>
<entry filename="C:\\SudarsanSRINIVASAN\\dev\\thirdface\\source\\thirdfaceView.mc" id="18" lineNum="435" parent="globals/thirdfaceView" pc="268437403" symbol="drawProgressCW"/>
<entry filename="C:\\SudarsanSRINIVASAN\\dev\\thirdface\\source\\thirdfaceView.mc" id="18" lineNum="436" parent="globals/thirdfaceView" pc="268437419" symbol="drawProgressCW"/>
<entry filename="C:\\SudarsanSRINIVASAN\\dev\\thirdface\\source\\thirdfaceView.mc" id="18" lineNum="437" parent="globals/thirdfaceView" pc="268437433" symbol="drawProgressCW"/>
<entry filename="C:\\SudarsanSRINIVASAN\\dev\\thirdface\\source\\thirdfaceView.mc" id="20" lineNum="454" parent="globals/thirdfaceView" pc="268437464" symbol="getXFromAngle"/>
<entry filename="C:\\SudarsanSRINIVASAN\\dev\\thirdface\\source\\thirdfaceView.mc" id="20" lineNum="455" parent="globals/thirdfaceView" pc="268437468" symbol="getXFromAngle"/>
<entry filename="C:\\SudarsanSRINIVASAN\\dev\\thirdface\\source\\thirdfaceView.mc" id="20" lineNum="456" parent="globals/thirdfaceView" pc="268437504" symbol="getXFromAngle"/>
<entry filename="C:\\SudarsanSRINIVASAN\\dev\\thirdface\\source\\thirdfaceView.mc" id="22" lineNum="74" parent="globals/thirdfaceView" pc="268437507" symbol="onLayout"/>
<entry filename="C:\\SudarsanSRINIVASAN\\dev\\thirdface\\source\\thirdfaceView.mc" id="22" lineNum="75" parent="globals/thirdfaceView" pc="268437509" symbol="onLayout"/>
<entry filename="C:\\SudarsanSRINIVASAN\\dev\\thirdface\\source\\thirdfaceView.mc" id="22" lineNum="76" parent="globals/thirdfaceView" pc="268437550" symbol="onLayout"/>
<entry filename="C:\\SudarsanSRINIVASAN\\dev\\thirdface\\source\\thirdfaceView.mc" id="22" lineNum="77" parent="globals/thirdfaceView" pc="268437597" symbol="onLayout"/>
<entry filename="C:\\SudarsanSRINIVASAN\\dev\\thirdface\\source\\thirdfaceView.mc" id="22" lineNum="78" parent="globals/thirdfaceView" pc="268437644" symbol="onLayout"/>
<entry filename="C:\\SudarsanSRINIVASAN\\dev\\thirdface\\source\\thirdfaceView.mc" id="22" lineNum="79" parent="globals/thirdfaceView" pc="268437691" symbol="onLayout"/>
<entry filename="C:\\SudarsanSRINIVASAN\\dev\\thirdface\\source\\thirdfaceView.mc" id="22" lineNum="80" parent="globals/thirdfaceView" pc="268437738" symbol="onLayout"/>
<entry filename="C:\\SudarsanSRINIVASAN\\dev\\thirdface\\source\\thirdfaceView.mc" id="22" lineNum="82" parent="globals/thirdfaceView" pc="268437785" symbol="onLayout"/>
<entry filename="C:\\SudarsanSRINIVASAN\\dev\\thirdface\\source\\thirdfaceView.mc" id="22" lineNum="83" parent="globals/thirdfaceView" pc="268437810" symbol="onLayout"/>
<entry filename="C:\\SudarsanSRINIVASAN\\dev\\thirdface\\source\\thirdfaceView.mc" id="22" lineNum="84" parent="globals/thirdfaceView" pc="268437829" symbol="onLayout"/>
<entry filename="C:\\SudarsanSRINIVASAN\\dev\\thirdface\\source\\thirdfaceView.mc" id="22" lineNum="85" parent="globals/thirdfaceView" pc="268437848" symbol="onLayout"/>
<entry filename="C:\\SudarsanSRINIVASAN\\dev\\thirdface\\source\\thirdfaceView.mc" id="22" lineNum="86" parent="globals/thirdfaceView" pc="268437870" symbol="onLayout"/>
<entry filename="C:\\SudarsanSRINIVASAN\\dev\\thirdface\\source\\thirdfaceView.mc" id="22" lineNum="88" parent="globals/thirdfaceView" pc="268437892" symbol="onLayout"/>
<entry filename="C:\\SudarsanSRINIVASAN\\dev\\thirdface\\source\\thirdfaceView.mc" id="22" lineNum="89" parent="globals/thirdfaceView" pc="268437937" symbol="onLayout"/>
<entry filename="C:\\SudarsanSRINIVASAN\\dev\\thirdface\\source\\thirdfaceView.mc" id="23" lineNum="201" parent="globals/thirdfaceView" pc="268437967" symbol="getJulianDate"/>
<entry filename="C:\\SudarsanSRINIVASAN\\dev\\thirdface\\source\\thirdfaceView.mc" id="23" lineNum="204" parent="globals/thirdfaceView" pc="268437971" symbol="getJulianDate"/>
<entry filename="C:\\SudarsanSRINIVASAN\\dev\\thirdface\\source\\thirdfaceView.mc" id="23" lineNum="203" parent="globals/thirdfaceView" pc="268437971" symbol="getJulianDate"/>
<entry filename="C:\\SudarsanSRINIVASAN\\dev\\thirdface\\source\\thirdfaceView.mc" id="23" lineNum="206" parent="globals/thirdfaceView" pc="268437971" symbol="getJulianDate"/>
<entry filename="C:\\SudarsanSRINIVASAN\\dev\\thirdface\\source\\thirdfaceView.mc" id="23" lineNum="202" parent="globals/thirdfaceView" pc="268437971" symbol="getJulianDate"/>
<entry filename="C:\\SudarsanSRINIVASAN\\dev\\thirdface\\source\\thirdfaceView.mc" id="23" lineNum="207" parent="globals/thirdfaceView" pc="268437990" symbol="getJulianDate"/>
<entry filename="C:\\SudarsanSRINIVASAN\\dev\\thirdface\\source\\thirdfaceView.mc" id="23" lineNum="208" parent="globals/thirdfaceView" pc="268438000" symbol="getJulianDate"/>
<entry filename="C:\\SudarsanSRINIVASAN\\dev\\thirdface\\source\\thirdfaceView.mc" id="23" lineNum="209" parent="globals/thirdfaceView" pc="268438011" symbol="getJulianDate"/>
<entry filename="C:\\SudarsanSRINIVASAN\\dev\\thirdface\\source\\thirdfaceView.mc" id="23" lineNum="211" parent="globals/thirdfaceView" pc="268438021" symbol="getJulianDate"/>
<entry filename="C:\\SudarsanSRINIVASAN\\dev\\thirdface\\source\\thirdfaceView.mc" id="23" lineNum="212" parent="globals/thirdfaceView" pc="268438037" symbol="getJulianDate"/>
<entry filename="C:\\SudarsanSRINIVASAN\\dev\\thirdface\\source\\thirdfaceView.mc" id="23" lineNum="213" parent="globals/thirdfaceView" pc="268438053" symbol="getJulianDate"/>
<entry filename="C:\\SudarsanSRINIVASAN\\dev\\thirdface\\source\\thirdfaceView.mc" id="23" lineNum="215" parent="globals/thirdfaceView" pc="268438081" symbol="getJulianDate"/>
<entry filename="C:\\SudarsanSRINIVASAN\\dev\\thirdface\\source\\thirdfaceView.mc" id="23" lineNum="216" parent="globals/thirdfaceView" pc="268438097" symbol="getJulianDate"/>
<entry filename="C:\\SudarsanSRINIVASAN\\dev\\thirdface\\source\\thirdfaceView.mc" id="23" lineNum="218" parent="globals/thirdfaceView" pc="268438108" symbol="getJulianDate"/>
<entry filename="C:\\SudarsanSRINIVASAN\\dev\\thirdface\\source\\thirdfaceView.mc" id="23" lineNum="220" parent="globals/thirdfaceView" pc="268438115" symbol="getJulianDate"/>
<entry filename="C:\\SudarsanSRINIVASAN\\dev\\thirdface\\source\\thirdfaceView.mc" id="24" lineNum="264" parent="globals/thirdfaceView" pc="268438118" symbol="getFriendlyCondition"/>
<entry filename="C:\\SudarsanSRINIVASAN\\dev\\thirdface\\source\\thirdfaceView.mc" id="24" lineNum="265" parent="globals/thirdfaceView" pc="268438120" symbol="getFriendlyCondition"/>
<entry filename="C:\\SudarsanSRINIVASAN\\dev\\thirdface\\source\\thirdfaceView.mc" id="24" lineNum="266" parent="globals/thirdfaceView" pc="268438131" symbol="getFriendlyCondition"/>
<entry filename="C:\\SudarsanSRINIVASAN\\dev\\thirdface\\source\\thirdfaceView.mc" id="24" lineNum="268" parent="globals/thirdfaceView" pc="268438140" symbol="getFriendlyCondition"/>
<entry filename="C:\\SudarsanSRINIVASAN\\dev\\thirdface\\source\\thirdfaceView.mc" id="24" lineNum="269" parent="globals/thirdfaceView" pc="268438151" symbol="getFriendlyCondition"/>
<entry filename="C:\\SudarsanSRINIVASAN\\dev\\thirdface\\source\\thirdfaceView.mc" id="24" lineNum="271" parent="globals/thirdfaceView" pc="268438160" symbol="getFriendlyCondition"/>
<entry filename="C:\\SudarsanSRINIVASAN\\dev\\thirdface\\source\\thirdfaceView.mc" id="24" lineNum="272" parent="globals/thirdfaceView" pc="268438171" symbol="getFriendlyCondition"/>
<entry filename="C:\\SudarsanSRINIVASAN\\dev\\thirdface\\source\\thirdfaceView.mc" id="24" lineNum="274" parent="globals/thirdfaceView" pc="268438180" symbol="getFriendlyCondition"/>
<entry filename="C:\\SudarsanSRINIVASAN\\dev\\thirdface\\source\\thirdfaceView.mc" id="24" lineNum="275" parent="globals/thirdfaceView" pc="268438191" symbol="getFriendlyCondition"/>
<entry filename="C:\\SudarsanSRINIVASAN\\dev\\thirdface\\source\\thirdfaceView.mc" id="24" lineNum="277" parent="globals/thirdfaceView" pc="268438200" symbol="getFriendlyCondition"/>
<entry filename="C:\\SudarsanSRINIVASAN\\dev\\thirdface\\source\\thirdfaceView.mc" id="24" lineNum="278" parent="globals/thirdfaceView" pc="268438211" symbol="getFriendlyCondition"/>
<entry filename="C:\\SudarsanSRINIVASAN\\dev\\thirdface\\source\\thirdfaceView.mc" id="24" lineNum="280" parent="globals/thirdfaceView" pc="268438220" symbol="getFriendlyCondition"/>
<entry filename="C:\\SudarsanSRINIVASAN\\dev\\thirdface\\source\\thirdfaceView.mc" id="24" lineNum="281" parent="globals/thirdfaceView" pc="268438231" symbol="getFriendlyCondition"/>
<entry filename="C:\\SudarsanSRINIVASAN\\dev\\thirdface\\source\\thirdfaceView.mc" id="24" lineNum="283" parent="globals/thirdfaceView" pc="268438240" symbol="getFriendlyCondition"/>
<entry filename="C:\\SudarsanSRINIVASAN\\dev\\thirdface\\source\\thirdfaceView.mc" id="24" lineNum="284" parent="globals/thirdfaceView" pc="268438251" symbol="getFriendlyCondition"/>
<entry filename="C:\\SudarsanSRINIVASAN\\dev\\thirdface\\source\\thirdfaceView.mc" id="24" lineNum="286" parent="globals/thirdfaceView" pc="268438260" symbol="getFriendlyCondition"/>
<entry filename="C:\\SudarsanSRINIVASAN\\dev\\thirdface\\source\\thirdfaceView.mc" id="24" lineNum="287" parent="globals/thirdfaceView" pc="268438271" symbol="getFriendlyCondition"/>
<entry filename="C:\\SudarsanSRINIVASAN\\dev\\thirdface\\source\\thirdfaceView.mc" id="24" lineNum="289" parent="globals/thirdfaceView" pc="268438280" symbol="getFriendlyCondition"/>
<entry filename="C:\\SudarsanSRINIVASAN\\dev\\thirdface\\source\\thirdfaceView.mc" id="24" lineNum="290" parent="globals/thirdfaceView" pc="268438291" symbol="getFriendlyCondition"/>
<entry filename="C:\\SudarsanSRINIVASAN\\dev\\thirdface\\source\\thirdfaceView.mc" id="24" lineNum="292" parent="globals/thirdfaceView" pc="268438300" symbol="getFriendlyCondition"/>
<entry filename="C:\\SudarsanSRINIVASAN\\dev\\thirdface\\source\\thirdfaceView.mc" id="24" lineNum="293" parent="globals/thirdfaceView" pc="268438311" symbol="getFriendlyCondition"/>
<entry filename="C:\\SudarsanSRINIVASAN\\dev\\thirdface\\source\\thirdfaceView.mc" id="24" lineNum="295" parent="globals/thirdfaceView" pc="268438320" symbol="getFriendlyCondition"/>
<entry filename="C:\\SudarsanSRINIVASAN\\dev\\thirdface\\source\\thirdfaceView.mc" id="24" lineNum="296" parent="globals/thirdfaceView" pc="268438331" symbol="getFriendlyCondition"/>
<entry filename="C:\\SudarsanSRINIVASAN\\dev\\thirdface\\source\\thirdfaceView.mc" id="24" lineNum="298" parent="globals/thirdfaceView" pc="268438340" symbol="getFriendlyCondition"/>
<entry filename="C:\\SudarsanSRINIVASAN\\dev\\thirdface\\source\\thirdfaceView.mc" id="24" lineNum="299" parent="globals/thirdfaceView" pc="268438351" symbol="getFriendlyCondition"/>
<entry filename="C:\\SudarsanSRINIVASAN\\dev\\thirdface\\source\\thirdfaceView.mc" id="24" lineNum="301" parent="globals/thirdfaceView" pc="268438360" symbol="getFriendlyCondition"/>
<entry filename="C:\\SudarsanSRINIVASAN\\dev\\thirdface\\source\\thirdfaceView.mc" id="24" lineNum="302" parent="globals/thirdfaceView" pc="268438371" symbol="getFriendlyCondition"/>
<entry filename="C:\\SudarsanSRINIVASAN\\dev\\thirdface\\source\\thirdfaceView.mc" id="24" lineNum="304" parent="globals/thirdfaceView" pc="268438380" symbol="getFriendlyCondition"/>
<entry filename="C:\\SudarsanSRINIVASAN\\dev\\thirdface\\source\\thirdfaceView.mc" id="24" lineNum="305" parent="globals/thirdfaceView" pc="268438391" symbol="getFriendlyCondition"/>
<entry filename="C:\\SudarsanSRINIVASAN\\dev\\thirdface\\source\\thirdfaceView.mc" id="24" lineNum="307" parent="globals/thirdfaceView" pc="268438400" symbol="getFriendlyCondition"/>
<entry filename="C:\\SudarsanSRINIVASAN\\dev\\thirdface\\source\\thirdfaceView.mc" id="24" lineNum="308" parent="globals/thirdfaceView" pc="268438411" symbol="getFriendlyCondition"/>
<entry filename="C:\\SudarsanSRINIVASAN\\dev\\thirdface\\source\\thirdfaceView.mc" id="24" lineNum="310" parent="globals/thirdfaceView" pc="268438420" symbol="getFriendlyCondition"/>
<entry filename="C:\\SudarsanSRINIVASAN\\dev\\thirdface\\source\\thirdfaceView.mc" id="24" lineNum="311" parent="globals/thirdfaceView" pc="268438431" symbol="getFriendlyCondition"/>
<entry filename="C:\\SudarsanSRINIVASAN\\dev\\thirdface\\source\\thirdfaceView.mc" id="24" lineNum="313" parent="globals/thirdfaceView" pc="268438440" symbol="getFriendlyCondition"/>
<entry filename="C:\\SudarsanSRINIVASAN\\dev\\thirdface\\source\\thirdfaceView.mc" id="24" lineNum="314" parent="globals/thirdfaceView" pc="268438451" symbol="getFriendlyCondition"/>
<entry filename="C:\\SudarsanSRINIVASAN\\dev\\thirdface\\source\\thirdfaceView.mc" id="24" lineNum="316" parent="globals/thirdfaceView" pc="268438460" symbol="getFriendlyCondition"/>
<entry filename="C:\\SudarsanSRINIVASAN\\dev\\thirdface\\source\\thirdfaceView.mc" id="24" lineNum="317" parent="globals/thirdfaceView" pc="268438471" symbol="getFriendlyCondition"/>
<entry filename="C:\\SudarsanSRINIVASAN\\dev\\thirdface\\source\\thirdfaceView.mc" id="24" lineNum="319" parent="globals/thirdfaceView" pc="268438480" symbol="getFriendlyCondition"/>
<entry filename="C:\\SudarsanSRINIVASAN\\dev\\thirdface\\source\\thirdfaceView.mc" id="24" lineNum="320" parent="globals/thirdfaceView" pc="268438491" symbol="getFriendlyCondition"/>
<entry filename="C:\\SudarsanSRINIVASAN\\dev\\thirdface\\source\\thirdfaceView.mc" id="24" lineNum="322" parent="globals/thirdfaceView" pc="268438500" symbol="getFriendlyCondition"/>
<entry filename="C:\\SudarsanSRINIVASAN\\dev\\thirdface\\source\\thirdfaceView.mc" id="24" lineNum="323" parent="globals/thirdfaceView" pc="268438511" symbol="getFriendlyCondition"/>
<entry filename="C:\\SudarsanSRINIVASAN\\dev\\thirdface\\source\\thirdfaceView.mc" id="24" lineNum="325" parent="globals/thirdfaceView" pc="268438520" symbol="getFriendlyCondition"/>
<entry filename="C:\\SudarsanSRINIVASAN\\dev\\thirdface\\source\\thirdfaceView.mc" id="24" lineNum="326" parent="globals/thirdfaceView" pc="268438531" symbol="getFriendlyCondition"/>
<entry filename="C:\\SudarsanSRINIVASAN\\dev\\thirdface\\source\\thirdfaceView.mc" id="24" lineNum="328" parent="globals/thirdfaceView" pc="268438540" symbol="getFriendlyCondition"/>
<entry filename="C:\\SudarsanSRINIVASAN\\dev\\thirdface\\source\\thirdfaceView.mc" id="24" lineNum="329" parent="globals/thirdfaceView" pc="268438551" symbol="getFriendlyCondition"/>
<entry filename="C:\\SudarsanSRINIVASAN\\dev\\thirdface\\source\\thirdfaceView.mc" id="24" lineNum="331" parent="globals/thirdfaceView" pc="268438560" symbol="getFriendlyCondition"/>
<entry filename="C:\\SudarsanSRINIVASAN\\dev\\thirdface\\source\\thirdfaceView.mc" id="24" lineNum="332" parent="globals/thirdfaceView" pc="268438571" symbol="getFriendlyCondition"/>
<entry filename="C:\\SudarsanSRINIVASAN\\dev\\thirdface\\source\\thirdfaceView.mc" id="24" lineNum="334" parent="globals/thirdfaceView" pc="268438580" symbol="getFriendlyCondition"/>
<entry filename="C:\\SudarsanSRINIVASAN\\dev\\thirdface\\source\\thirdfaceView.mc" id="24" lineNum="335" parent="globals/thirdfaceView" pc="268438591" symbol="getFriendlyCondition"/>
<entry filename="C:\\SudarsanSRINIVASAN\\dev\\thirdface\\source\\thirdfaceView.mc" id="24" lineNum="337" parent="globals/thirdfaceView" pc="268438600" symbol="getFriendlyCondition"/>
<entry filename="C:\\SudarsanSRINIVASAN\\dev\\thirdface\\source\\thirdfaceView.mc" id="24" lineNum="338" parent="globals/thirdfaceView" pc="268438611" symbol="getFriendlyCondition"/>
<entry filename="C:\\SudarsanSRINIVASAN\\dev\\thirdface\\source\\thirdfaceView.mc" id="24" lineNum="340" parent="globals/thirdfaceView" pc="268438620" symbol="getFriendlyCondition"/>
<entry filename="C:\\SudarsanSRINIVASAN\\dev\\thirdface\\source\\thirdfaceView.mc" id="24" lineNum="341" parent="globals/thirdfaceView" pc="268438631" symbol="getFriendlyCondition"/>
<entry filename="C:\\SudarsanSRINIVASAN\\dev\\thirdface\\source\\thirdfaceView.mc" id="24" lineNum="343" parent="globals/thirdfaceView" pc="268438640" symbol="getFriendlyCondition"/>
<entry filename="C:\\SudarsanSRINIVASAN\\dev\\thirdface\\source\\thirdfaceView.mc" id="24" lineNum="344" parent="globals/thirdfaceView" pc="268438651" symbol="getFriendlyCondition"/>
<entry filename="C:\\SudarsanSRINIVASAN\\dev\\thirdface\\source\\thirdfaceView.mc" id="24" lineNum="346" parent="globals/thirdfaceView" pc="268438660" symbol="getFriendlyCondition"/>
<entry filename="C:\\SudarsanSRINIVASAN\\dev\\thirdface\\source\\thirdfaceView.mc" id="24" lineNum="347" parent="globals/thirdfaceView" pc="268438671" symbol="getFriendlyCondition"/>
<entry filename="C:\\SudarsanSRINIVASAN\\dev\\thirdface\\source\\thirdfaceView.mc" id="24" lineNum="349" parent="globals/thirdfaceView" pc="268438680" symbol="getFriendlyCondition"/>
<entry filename="C:\\SudarsanSRINIVASAN\\dev\\thirdface\\source\\thirdfaceView.mc" id="24" lineNum="350" parent="globals/thirdfaceView" pc="268438691" symbol="getFriendlyCondition"/>
<entry filename="C:\\SudarsanSRINIVASAN\\dev\\thirdface\\source\\thirdfaceView.mc" id="24" lineNum="352" parent="globals/thirdfaceView" pc="268438700" symbol="getFriendlyCondition"/>
<entry filename="C:\\SudarsanSRINIVASAN\\dev\\thirdface\\source\\thirdfaceView.mc" id="24" lineNum="353" parent="globals/thirdfaceView" pc="268438711" symbol="getFriendlyCondition"/>
<entry filename="C:\\SudarsanSRINIVASAN\\dev\\thirdface\\source\\thirdfaceView.mc" id="24" lineNum="355" parent="globals/thirdfaceView" pc="268438720" symbol="getFriendlyCondition"/>
<entry filename="C:\\SudarsanSRINIVASAN\\dev\\thirdface\\source\\thirdfaceView.mc" id="24" lineNum="356" parent="globals/thirdfaceView" pc="268438731" symbol="getFriendlyCondition"/>
<entry filename="C:\\SudarsanSRINIVASAN\\dev\\thirdface\\source\\thirdfaceView.mc" id="24" lineNum="358" parent="globals/thirdfaceView" pc="268438740" symbol="getFriendlyCondition"/>
<entry filename="C:\\SudarsanSRINIVASAN\\dev\\thirdface\\source\\thirdfaceView.mc" id="24" lineNum="359" parent="globals/thirdfaceView" pc="268438751" symbol="getFriendlyCondition"/>
<entry filename="C:\\SudarsanSRINIVASAN\\dev\\thirdface\\source\\thirdfaceView.mc" id="24" lineNum="361" parent="globals/thirdfaceView" pc="268438760" symbol="getFriendlyCondition"/>
<entry filename="C:\\SudarsanSRINIVASAN\\dev\\thirdface\\source\\thirdfaceView.mc" id="24" lineNum="362" parent="globals/thirdfaceView" pc="268438771" symbol="getFriendlyCondition"/>
<entry filename="C:\\SudarsanSRINIVASAN\\dev\\thirdface\\source\\thirdfaceView.mc" id="24" lineNum="364" parent="globals/thirdfaceView" pc="268438780" symbol="getFriendlyCondition"/>
<entry filename="C:\\SudarsanSRINIVASAN\\dev\\thirdface\\source\\thirdfaceView.mc" id="24" lineNum="365" parent="globals/thirdfaceView" pc="268438791" symbol="getFriendlyCondition"/>
<entry filename="C:\\SudarsanSRINIVASAN\\dev\\thirdface\\source\\thirdfaceView.mc" id="24" lineNum="367" parent="globals/thirdfaceView" pc="268438800" symbol="getFriendlyCondition"/>
<entry filename="C:\\SudarsanSRINIVASAN\\dev\\thirdface\\source\\thirdfaceView.mc" id="24" lineNum="368" parent="globals/thirdfaceView" pc="268438811" symbol="getFriendlyCondition"/>
<entry filename="C:\\SudarsanSRINIVASAN\\dev\\thirdface\\source\\thirdfaceView.mc" id="24" lineNum="370" parent="globals/thirdfaceView" pc="268438820" symbol="getFriendlyCondition"/>
<entry filename="C:\\SudarsanSRINIVASAN\\dev\\thirdface\\source\\thirdfaceView.mc" id="24" lineNum="371" parent="globals/thirdfaceView" pc="268438831" symbol="getFriendlyCondition"/>
<entry filename="C:\\SudarsanSRINIVASAN\\dev\\thirdface\\source\\thirdfaceView.mc" id="24" lineNum="373" parent="globals/thirdfaceView" pc="268438840" symbol="getFriendlyCondition"/>
<entry filename="C:\\SudarsanSRINIVASAN\\dev\\thirdface\\source\\thirdfaceView.mc" id="24" lineNum="374" parent="globals/thirdfaceView" pc="268438851" symbol="getFriendlyCondition"/>
<entry filename="C:\\SudarsanSRINIVASAN\\dev\\thirdface\\source\\thirdfaceView.mc" id="24" lineNum="376" parent="globals/thirdfaceView" pc="268438860" symbol="getFriendlyCondition"/>
<entry filename="C:\\SudarsanSRINIVASAN\\dev\\thirdface\\source\\thirdfaceView.mc" id="24" lineNum="377" parent="globals/thirdfaceView" pc="268438871" symbol="getFriendlyCondition"/>
<entry filename="C:\\SudarsanSRINIVASAN\\dev\\thirdface\\source\\thirdfaceView.mc" id="24" lineNum="379" parent="globals/thirdfaceView" pc="268438880" symbol="getFriendlyCondition"/>
<entry filename="C:\\SudarsanSRINIVASAN\\dev\\thirdface\\source\\thirdfaceView.mc" id="24" lineNum="380" parent="globals/thirdfaceView" pc="268438891" symbol="getFriendlyCondition"/>
<entry filename="C:\\SudarsanSRINIVASAN\\dev\\thirdface\\source\\thirdfaceView.mc" id="24" lineNum="382" parent="globals/thirdfaceView" pc="268438900" symbol="getFriendlyCondition"/>
<entry filename="C:\\SudarsanSRINIVASAN\\dev\\thirdface\\source\\thirdfaceView.mc" id="24" lineNum="383" parent="globals/thirdfaceView" pc="268438911" symbol="getFriendlyCondition"/>
<entry filename="C:\\SudarsanSRINIVASAN\\dev\\thirdface\\source\\thirdfaceView.mc" id="24" lineNum="385" parent="globals/thirdfaceView" pc="268438920" symbol="getFriendlyCondition"/>
<entry filename="C:\\SudarsanSRINIVASAN\\dev\\thirdface\\source\\thirdfaceView.mc" id="24" lineNum="386" parent="globals/thirdfaceView" pc="268438931" symbol="getFriendlyCondition"/>
<entry filename="C:\\SudarsanSRINIVASAN\\dev\\thirdface\\source\\thirdfaceView.mc" id="24" lineNum="388" parent="globals/thirdfaceView" pc="268438940" symbol="getFriendlyCondition"/>
<entry filename="C:\\SudarsanSRINIVASAN\\dev\\thirdface\\source\\thirdfaceView.mc" id="24" lineNum="389" parent="globals/thirdfaceView" pc="268438951" symbol="getFriendlyCondition"/>
<entry filename="C:\\SudarsanSRINIVASAN\\dev\\thirdface\\source\\thirdfaceView.mc" id="24" lineNum="391" parent="globals/thirdfaceView" pc="268438960" symbol="getFriendlyCondition"/>
<entry filename="C:\\SudarsanSRINIVASAN\\dev\\thirdface\\source\\thirdfaceView.mc" id="24" lineNum="392" parent="globals/thirdfaceView" pc="268438971" symbol="getFriendlyCondition"/>
<entry filename="C:\\SudarsanSRINIVASAN\\dev\\thirdface\\source\\thirdfaceView.mc" id="24" lineNum="394" parent="globals/thirdfaceView" pc="268438980" symbol="getFriendlyCondition"/>
<entry filename="C:\\SudarsanSRINIVASAN\\dev\\thirdface\\source\\thirdfaceView.mc" id="24" lineNum="395" parent="globals/thirdfaceView" pc="268438991" symbol="getFriendlyCondition"/>
<entry filename="C:\\SudarsanSRINIVASAN\\dev\\thirdface\\source\\thirdfaceView.mc" id="24" lineNum="397" parent="globals/thirdfaceView" pc="268439000" symbol="getFriendlyCondition"/>
<entry filename="C:\\SudarsanSRINIVASAN\\dev\\thirdface\\source\\thirdfaceView.mc" id="24" lineNum="398" parent="globals/thirdfaceView" pc="268439011" symbol="getFriendlyCondition"/>
<entry filename="C:\\SudarsanSRINIVASAN\\dev\\thirdface\\source\\thirdfaceView.mc" id="24" lineNum="400" parent="globals/thirdfaceView" pc="268439020" symbol="getFriendlyCondition"/>
<entry filename="C:\\SudarsanSRINIVASAN\\dev\\thirdface\\source\\thirdfaceView.mc" id="24" lineNum="401" parent="globals/thirdfaceView" pc="268439031" symbol="getFriendlyCondition"/>
<entry filename="C:\\SudarsanSRINIVASAN\\dev\\thirdface\\source\\thirdfaceView.mc" id="24" lineNum="403" parent="globals/thirdfaceView" pc="268439040" symbol="getFriendlyCondition"/>
<entry filename="C:\\SudarsanSRINIVASAN\\dev\\thirdface\\source\\thirdfaceView.mc" id="24" lineNum="404" parent="globals/thirdfaceView" pc="268439051" symbol="getFriendlyCondition"/>
<entry filename="C:\\SudarsanSRINIVASAN\\dev\\thirdface\\source\\thirdfaceView.mc" id="24" lineNum="406" parent="globals/thirdfaceView" pc="268439060" symbol="getFriendlyCondition"/>
<entry filename="C:\\SudarsanSRINIVASAN\\dev\\thirdface\\source\\thirdfaceView.mc" id="24" lineNum="407" parent="globals/thirdfaceView" pc="268439071" symbol="getFriendlyCondition"/>
<entry filename="C:\\SudarsanSRINIVASAN\\dev\\thirdface\\source\\thirdfaceView.mc" id="24" lineNum="409" parent="globals/thirdfaceView" pc="268439080" symbol="getFriendlyCondition"/>
<entry filename="C:\\SudarsanSRINIVASAN\\dev\\thirdface\\source\\thirdfaceView.mc" id="24" lineNum="410" parent="globals/thirdfaceView" pc="268439091" symbol="getFriendlyCondition"/>
<entry filename="C:\\SudarsanSRINIVASAN\\dev\\thirdface\\source\\thirdfaceView.mc" id="24" lineNum="412" parent="globals/thirdfaceView" pc="268439100" symbol="getFriendlyCondition"/>
<entry filename="C:\\SudarsanSRINIVASAN\\dev\\thirdface\\source\\thirdfaceView.mc" id="24" lineNum="413" parent="globals/thirdfaceView" pc="268439111" symbol="getFriendlyCondition"/>
<entry filename="C:\\SudarsanSRINIVASAN\\dev\\thirdface\\source\\thirdfaceView.mc" id="24" lineNum="415" parent="globals/thirdfaceView" pc="268439120" symbol="getFriendlyCondition"/>
<entry filename="C:\\SudarsanSRINIVASAN\\dev\\thirdface\\source\\thirdfaceView.mc" id="24" lineNum="416" parent="globals/thirdfaceView" pc="268439131" symbol="getFriendlyCondition"/>
<entry filename="C:\\SudarsanSRINIVASAN\\dev\\thirdface\\source\\thirdfaceView.mc" id="24" lineNum="418" parent="globals/thirdfaceView" pc="268439140" symbol="getFriendlyCondition"/>
<entry filename="C:\\SudarsanSRINIVASAN\\dev\\thirdface\\source\\thirdfaceView.mc" id="24" lineNum="419" parent="globals/thirdfaceView" pc="268439151" symbol="getFriendlyCondition"/>
<entry filename="C:\\SudarsanSRINIVASAN\\dev\\thirdface\\source\\thirdfaceView.mc" id="24" lineNum="421" parent="globals/thirdfaceView" pc="268439160" symbol="getFriendlyCondition"/>
<entry filename="C:\\SudarsanSRINIVASAN\\dev\\thirdface\\source\\thirdfaceView.mc" id="24" lineNum="422" parent="globals/thirdfaceView" pc="268439171" symbol="getFriendlyCondition"/>
<entry filename="C:\\SudarsanSRINIVASAN\\dev\\thirdface\\source\\thirdfaceView.mc" id="24" lineNum="424" parent="globals/thirdfaceView" pc="268439180" symbol="getFriendlyCondition"/>
<entry filename="C:\\SudarsanSRINIVASAN\\dev\\thirdface\\source\\thirdfaceView.mc" id="24" lineNum="425" parent="globals/thirdfaceView" pc="268439191" symbol="getFriendlyCondition"/>
<entry filename="C:\\SudarsanSRINIVASAN\\dev\\thirdface\\source\\thirdfaceView.mc" id="24" lineNum="428" parent="globals/thirdfaceView" pc="268439200" symbol="getFriendlyCondition"/>
<entry filename="C:\\SudarsanSRINIVASAN\\dev\\thirdface\\source\\thirdfaceView.mc" id="26" lineNum="69" parent="globals/thirdfaceView" pc="268439207" symbol="initialize"/>
<entry filename="C:\\SudarsanSRINIVASAN\\dev\\thirdface\\source\\thirdfaceView.mc" id="26" lineNum="70" parent="globals/thirdfaceView" pc="268439209" symbol="initialize"/>
<entry filename="C:\\SudarsanSRINIVASAN\\dev\\thirdface\\source\\thirdfaceView.mc" id="27" lineNum="99" parent="globals/thirdfaceView" pc="268439228" symbol="onUpdate"/>
<entry filename="C:\\SudarsanSRINIVASAN\\dev\\thirdface\\source\\thirdfaceView.mc" id="27" lineNum="101" parent="globals/thirdfaceView" pc="268439232" symbol="onUpdate"/>
<entry filename="C:\\SudarsanSRINIVASAN\\dev\\thirdface\\source\\thirdfaceView.mc" id="27" lineNum="104" parent="globals/thirdfaceView" pc="268439256" symbol="onUpdate"/>
<entry filename="C:\\SudarsanSRINIVASAN\\dev\\thirdface\\source\\thirdfaceView.mc" id="27" lineNum="107" parent="globals/thirdfaceView" pc="268439286" symbol="onUpdate"/>
<entry filename="C:\\SudarsanSRINIVASAN\\dev\\thirdface\\source\\thirdfaceView.mc" id="27" lineNum="108" parent="globals/thirdfaceView" pc="268439303" symbol="onUpdate"/>
<entry filename="C:\\SudarsanSRINIVASAN\\dev\\thirdface\\source\\thirdfaceView.mc" id="27" lineNum="109" parent="globals/thirdfaceView" pc="268439361" symbol="onUpdate"/>
<entry filename="C:\\SudarsanSRINIVASAN\\dev\\thirdface\\source\\thirdfaceView.mc" id="27" lineNum="110" parent="globals/thirdfaceView" pc="268439419" symbol="onUpdate"/>
<entry filename="C:\\SudarsanSRINIVASAN\\dev\\thirdface\\source\\thirdfaceView.mc" id="27" lineNum="113" parent="globals/thirdfaceView" pc="268439438" symbol="onUpdate"/>
<entry filename="C:\\SudarsanSRINIVASAN\\dev\\thirdface\\source\\thirdfaceView.mc" id="27" lineNum="116" parent="globals/thirdfaceView" pc="268439510" symbol="onUpdate"/>
<entry filename="C:\\SudarsanSRINIVASAN\\dev\\thirdface\\source\\thirdfaceView.mc" id="27" lineNum="117" parent="globals/thirdfaceView" pc="268439520" symbol="onUpdate"/>
<entry filename="C:\\SudarsanSRINIVASAN\\dev\\thirdface\\source\\thirdfaceView.mc" id="27" lineNum="118" parent="globals/thirdfaceView" pc="268439530" symbol="onUpdate"/>
<entry filename="C:\\SudarsanSRINIVASAN\\dev\\thirdface\\source\\thirdfaceView.mc" id="27" lineNum="119" parent="globals/thirdfaceView" pc="268439540" symbol="onUpdate"/>
<entry filename="C:\\SudarsanSRINIVASAN\\dev\\thirdface\\source\\thirdfaceView.mc" id="27" lineNum="122" parent="globals/thirdfaceView" pc="268439550" symbol="onUpdate"/>
<entry filename="C:\\SudarsanSRINIVASAN\\dev\\thirdface\\source\\thirdfaceView.mc" id="27" lineNum="125" parent="globals/thirdfaceView" pc="268439638" symbol="onUpdate"/>
<entry filename="C:\\SudarsanSRINIVASAN\\dev\\thirdface\\source\\thirdfaceView.mc" id="27" lineNum="126" parent="globals/thirdfaceView" pc="268439665" symbol="onUpdate"/>
<entry filename="C:\\SudarsanSRINIVASAN\\dev\\thirdface\\source\\thirdfaceView.mc" id="27" lineNum="127" parent="globals/thirdfaceView" pc="268439685" symbol="onUpdate"/>
<entry filename="C:\\SudarsanSRINIVASAN\\dev\\thirdface\\source\\thirdfaceView.mc" id="27" lineNum="128" parent="globals/thirdfaceView" pc="268439711" symbol="onUpdate"/>
<entry filename="C:\\SudarsanSRINIVASAN\\dev\\thirdface\\source\\thirdfaceView.mc" id="27" lineNum="129" parent="globals/thirdfaceView" pc="268439733" symbol="onUpdate"/>
<entry filename="C:\\SudarsanSRINIVASAN\\dev\\thirdface\\source\\thirdfaceView.mc" id="27" lineNum="132" parent="globals/thirdfaceView" pc="268439754" symbol="onUpdate"/>
<entry filename="C:\\SudarsanSRINIVASAN\\dev\\thirdface\\source\\thirdfaceView.mc" id="27" lineNum="133" parent="globals/thirdfaceView" pc="268439780" symbol="onUpdate"/>
<entry filename="C:\\SudarsanSRINIVASAN\\dev\\thirdface\\source\\thirdfaceView.mc" id="27" lineNum="134" parent="globals/thirdfaceView" pc="268439812" symbol="onUpdate"/>
<entry filename="C:\\SudarsanSRINIVASAN\\dev\\thirdface\\source\\thirdfaceView.mc" id="27" lineNum="135" parent="globals/thirdfaceView" pc="268439834" symbol="onUpdate"/>
<entry filename="C:\\SudarsanSRINIVASAN\\dev\\thirdface\\source\\thirdfaceView.mc" id="27" lineNum="138" parent="globals/thirdfaceView" pc="268439855" symbol="onUpdate"/>
<entry filename="C:\\SudarsanSRINIVASAN\\dev\\thirdface\\source\\thirdfaceView.mc" id="27" lineNum="139" parent="globals/thirdfaceView" pc="268439877" symbol="onUpdate"/>
<entry filename="C:\\SudarsanSRINIVASAN\\dev\\thirdface\\source\\thirdfaceView.mc" id="27" lineNum="140" parent="globals/thirdfaceView" pc="268439932" symbol="onUpdate"/>
<entry filename="C:\\SudarsanSRINIVASAN\\dev\\thirdface\\source\\thirdfaceView.mc" id="27" lineNum="141" parent="globals/thirdfaceView" pc="268439954" symbol="onUpdate"/>
<entry filename="C:\\SudarsanSRINIVASAN\\dev\\thirdface\\source\\thirdfaceView.mc" id="27" lineNum="144" parent="globals/thirdfaceView" pc="268440009" symbol="onUpdate"/>
<entry filename="C:\\SudarsanSRINIVASAN\\dev\\thirdface\\source\\thirdfaceView.mc" id="27" lineNum="145" parent="globals/thirdfaceView" pc="268440031" symbol="onUpdate"/>
<entry filename="C:\\SudarsanSRINIVASAN\\dev\\thirdface\\source\\thirdfaceView.mc" id="27" lineNum="148" parent="globals/thirdfaceView" pc="268440080" symbol="onUpdate"/>
<entry filename="C:\\SudarsanSRINIVASAN\\dev\\thirdface\\source\\thirdfaceView.mc" id="27" lineNum="149" parent="globals/thirdfaceView" pc="268440108" symbol="onUpdate"/>
<entry filename="C:\\SudarsanSRINIVASAN\\dev\\thirdface\\source\\thirdfaceView.mc" id="27" lineNum="150" parent="globals/thirdfaceView" pc="268440133" symbol="onUpdate"/>
<entry filename="C:\\SudarsanSRINIVASAN\\dev\\thirdface\\source\\thirdfaceView.mc" id="27" lineNum="151" parent="globals/thirdfaceView" pc="268440140" symbol="onUpdate"/>
<entry filename="C:\\SudarsanSRINIVASAN\\dev\\thirdface\\source\\thirdfaceView.mc" id="27" lineNum="152" parent="globals/thirdfaceView" pc="268440162" symbol="onUpdate"/>
<entry filename="C:\\SudarsanSRINIVASAN\\dev\\thirdface\\source\\thirdfaceView.mc" id="27" lineNum="156" parent="globals/thirdfaceView" pc="268440220" symbol="onUpdate"/>
<entry filename="C:\\SudarsanSRINIVASAN\\dev\\thirdface\\source\\thirdfaceView.mc" id="27" lineNum="158" parent="globals/thirdfaceView" pc="268440242" symbol="onUpdate"/>
<entry filename="C:\\SudarsanSRINIVASAN\\dev\\thirdface\\source\\thirdfaceView.mc" id="27" lineNum="159" parent="globals/thirdfaceView" pc="268440249" symbol="onUpdate"/>
<entry filename="C:\\SudarsanSRINIVASAN\\dev\\thirdface\\source\\thirdfaceView.mc" id="27" lineNum="160" parent="globals/thirdfaceView" pc="268440262" symbol="onUpdate"/>
<entry filename="C:\\SudarsanSRINIVASAN\\dev\\thirdface\\source\\thirdfaceView.mc" id="27" lineNum="161" parent="globals/thirdfaceView" pc="268440273" symbol="onUpdate"/>
<entry filename="C:\\SudarsanSRINIVASAN\\dev\\thirdface\\source\\thirdfaceView.mc" id="27" lineNum="165" parent="globals/thirdfaceView" pc="268440327" symbol="onUpdate"/>
<entry filename="C:\\SudarsanSRINIVASAN\\dev\\thirdface\\source\\thirdfaceView.mc" id="27" lineNum="166" parent="globals/thirdfaceView" pc="268440334" symbol="onUpdate"/>
<entry filename="C:\\SudarsanSRINIVASAN\\dev\\thirdface\\source\\thirdfaceView.mc" id="27" lineNum="167" parent="globals/thirdfaceView" pc="268440347" symbol="onUpdate"/>
<entry filename="C:\\SudarsanSRINIVASAN\\dev\\thirdface\\source\\thirdfaceView.mc" id="27" lineNum="168" parent="globals/thirdfaceView" pc="268440358" symbol="onUpdate"/>
<entry filename="C:\\SudarsanSRINIVASAN\\dev\\thirdface\\source\\thirdfaceView.mc" id="27" lineNum="172" parent="globals/thirdfaceView" pc="268440412" symbol="onUpdate"/>
<entry filename="C:\\SudarsanSRINIVASAN\\dev\\thirdface\\source\\thirdfaceView.mc" id="27" lineNum="173" parent="globals/thirdfaceView" pc="268440415" symbol="onUpdate"/>
<entry filename="C:\\SudarsanSRINIVASAN\\dev\\thirdface\\source\\thirdfaceView.mc" id="27" lineNum="174" parent="globals/thirdfaceView" pc="268440466" symbol="onUpdate"/>
<entry filename="C:\\SudarsanSRINIVASAN\\dev\\thirdface\\source\\thirdfaceView.mc" id="27" lineNum="175" parent="globals/thirdfaceView" pc="268440489" symbol="onUpdate"/>
<entry filename="C:\\SudarsanSRINIVASAN\\dev\\thirdface\\source\\thirdfaceView.mc" id="27" lineNum="176" parent="globals/thirdfaceView" pc="268440496" symbol="onUpdate"/>
<entry filename="C:\\SudarsanSRINIVASAN\\dev\\thirdface\\source\\thirdfaceView.mc" id="27" lineNum="178" parent="globals/thirdfaceView" pc="268440509" symbol="onUpdate"/>
<entry filename="C:\\SudarsanSRINIVASAN\\dev\\thirdface\\source\\thirdfaceView.mc" id="27" lineNum="179" parent="globals/thirdfaceView" pc="268440516" symbol="onUpdate"/>
<entry filename="C:\\SudarsanSRINIVASAN\\dev\\thirdface\\source\\thirdfaceView.mc" id="27" lineNum="182" parent="globals/thirdfaceView" pc="268440526" symbol="onUpdate"/>
<entry filename="C:\\SudarsanSRINIVASAN\\dev\\thirdface\\source\\thirdfaceView.mc" id="27" lineNum="183" parent="globals/thirdfaceView" pc="268440533" symbol="onUpdate"/>
<entry filename="C:\\SudarsanSRINIVASAN\\dev\\thirdface\\source\\thirdfaceView.mc" id="27" lineNum="184" parent="globals/thirdfaceView" pc="268440555" symbol="onUpdate"/>
<entry filename="C:\\SudarsanSRINIVASAN\\dev\\thirdface\\source\\thirdfaceView.mc" id="27" lineNum="188" parent="globals/thirdfaceView" pc="268440591" symbol="onUpdate"/>
<entry filename="C:\\SudarsanSRINIVASAN\\dev\\thirdface\\source\\thirdfaceView.mc" id="27" lineNum="189" parent="globals/thirdfaceView" pc="268440644" symbol="onUpdate"/>
<entry filename="C:\\SudarsanSRINIVASAN\\dev\\thirdface\\source\\thirdfaceView.mc" id="27" lineNum="190" parent="globals/thirdfaceView" pc="268440712" symbol="onUpdate"/>
<entry filename="C:\\SudarsanSRINIVASAN\\dev\\thirdface\\source\\thirdfaceView.mc" id="27" lineNum="191" parent="globals/thirdfaceView" pc="268440734" symbol="onUpdate"/>
<entry filename="C:\\SudarsanSRINIVASAN\\dev\\thirdface\\source\\thirdfaceView.mc" id="27" lineNum="192" parent="globals/thirdfaceView" pc="268440789" symbol="onUpdate"/>
<entry filename="C:\\SudarsanSRINIVASAN\\dev\\thirdface\\source\\thirdfaceView.mc" id="27" lineNum="193" parent="globals/thirdfaceView" pc="268440811" symbol="onUpdate"/>
<entry filename="C:\\SudarsanSRINIVASAN\\dev\\thirdface\\source\\thirdfaceView.mc" id="27" lineNum="197" parent="globals/thirdfaceView" pc="268440898" symbol="onUpdate"/>
<entry filename="C:\\SudarsanSRINIVASAN\\dev\\thirdface\\source\\thirdfaceView.mc" id="27" lineNum="198" parent="globals/thirdfaceView" pc="268440920" symbol="onUpdate"/>
<entry filename="c:\\SudarsanSRINIVASAN\\dev\\thirdface\\side_load\\gen\\006-B3851-00\\source\\Rez.mcgen" id="28" lineNum="24" parent="globals/Rez/Layouts" pc="268440978" symbol="WatchFace"/>
<entry filename="c:\\SudarsanSRINIVASAN\\dev\\thirdface\\side_load\\gen\\006-B3851-00\\source\\Rez.mcgen" id="28" lineNum="25" parent="globals/Rez/Layouts" pc="268440988" symbol="WatchFace"/>
</pcToLineNum>
<symbolTable>
<entry id="8388639" module="true" symbol="Graphics"/>
<entry id="10" object="true" symbol="thirdfaceApp"/>
<entry id="8388632" method="true" symbol="&lt;init&gt;"/>
<entry id="7" module="true" symbol="globals/Rez/Menus"/>
<entry id="28" method="true" symbol="getYFromAngle"/>
<entry id="8388924" module="true" symbol="Gregorian"/>
<entry id="8391839" method="true" symbol="getBodyBatteryHistory"/>
<entry field="true" id="8388611" module="true" symbol="Toybox"/>
<entry id="27" method="true" symbol="getXFromAngle"/>
<entry id="17" method="true" symbol="drawMoon"/>
<entry field="true" id="32" symbol="viewHeight"/>
<entry field="true" id="38" symbol="AppName"/>
<entry id="8" module="true" symbol="globals/Rez/Strings"/>
<entry id="8388772" module="true" object="true" symbol="Fonts"/>
<entry id="19" method="true" symbol="drawProgressCW"/>
<entry id="8388648" module="true" symbol="WatchUi"/>
<entry field="true" id="34" symbol="viewXCenter"/>
<entry id="2" module="true" symbol="globals/Rez"/>
<entry field="true" id="35" symbol="viewYCenter"/>
<entry id="8389124" method="true" symbol="onUpdate"/>
<entry id="8389375" method="true" object="true" symbol="WatchFace"/>
<entry id="8388771" module="true" object="true" symbol="Drawables"/>
<entry field="true" id="31" symbol="t2"/>
<entry field="true" id="30" symbol="t1"/>
<entry id="13" module="true" symbol="Menus"/>
<entry id="8389275" method="true" symbol="getApp"/>
<entry field="true" id="22" symbol="faceRadius"/>
<entry id="6" module="true" symbol="globals/Rez/Layouts"/>
<entry field="true" id="16" symbol="calInfo"/>
<entry id="8389122" method="true" symbol="onLayout"/>
<entry id="8389376" method="true" symbol="onEnterSleep"/>
<entry field="true" id="21" symbol="f2"/>
<entry field="true" id="20" symbol="f1"/>
<entry field="true" id="15" symbol="bg"/>
<entry field="true" id="29" symbol="hrIterator"/>
<entry id="5" module="true" symbol="globals/Rez/JsonData"/>
<entry id="3" module="true" symbol="globals/Rez/Drawables"/>
<entry id="24" method="true" symbol="getFriendlyCondition"/>
<entry id="9" object="true" symbol="thirdFaceDelegate"/>
<entry id="8389377" method="true" symbol="onExitSleep"/>
<entry id="8388644" module="true" symbol="System"/>
<entry id="8388769" module="true" object="true" symbol="Rez"/>
<entry id="23" method="true" symbol="getAngleFromTime"/>
<entry id="8388640" module="true" symbol="Lang"/>
<entry id="8390088" module="true" object="true" symbol="JsonData"/>
<entry field="true" id="36" symbol="LauncherIcon"/>
<entry id="8388610" symbol="statics"/>
<entry id="8389123" method="true" symbol="onShow"/>
<entry field="true" id="37" symbol="bgImage"/>
<entry id="26" method="true" symbol="getMoonAge"/>
<entry id="8389350" module="true" symbol="globals"/>
<entry id="8388770" module="true" object="true" symbol="Strings"/>
<entry id="8388702" method="true" symbol="initialize"/>
<entry id="8389279" method="true" symbol="onStart"/>
<entry id="18" method="true" symbol="drawProgressCCW"/>
<entry id="8389280" method="true" symbol="getInitialView"/>
<entry id="8389281" method="true" symbol="onStop"/>
<entry id="11" object="true" symbol="thirdfaceView"/>
<entry id="8389781" module="true" symbol="SensorHistory"/>
<entry id="8392031" method="true" symbol="onPress"/>
<entry field="true" id="33" symbol="viewWidth"/>
<entry id="12" module="true" symbol="Layouts"/>
<entry id="4" module="true" symbol="globals/Rez/Fonts"/>
<entry id="8389125" method="true" symbol="onHide"/>
<entry field="true" id="14" symbol="batt"/>
<entry id="8388635" module="true" symbol="Application"/>
<entry id="25" method="true" symbol="getJulianDate"/>
</symbolTable>
<localVars>
<entry arg="true" endPc="268436707" name="clickEvent" stackId="1" startPc="268435619"/>
<entry endPc="268436707" name="tapCoordinates" stackId="2" startPc="268435623"/>
<entry endPc="268436707" name="tapX" stackId="3" startPc="268435623"/>
<entry endPc="268436707" name="tapY" stackId="4" startPc="268435623"/>
<entry endPc="268436707" name="tapFlag" stackId="5" startPc="268435623"/>
<entry endPc="268435845" name="app" stackId="6" startPc="268435770"/>
<entry endPc="268435977" name="app" stackId="7" startPc="268435902"/>
<entry endPc="268436109" name="app" stackId="8" startPc="268436034"/>
<entry endPc="268436241" name="app" stackId="9" startPc="268436166"/>
<entry endPc="268436373" name="app" stackId="10" startPc="268436298"/>
<entry endPc="268436505" name="app" stackId="11" startPc="268436430"/>
<entry endPc="268436637" name="app" stackId="12" startPc="268436562"/>
<entry endPc="268436699" name="ex" stackId="13" startPc="268436668"/>
<entry arg="true" endPc="268436910" name="d" stackId="1" startPc="268436772"/>
<entry arg="true" endPc="268436910" name="m" stackId="2" startPc="268436772"/>
<entry arg="true" endPc="268436910" name="y" stackId="3" startPc="268436772"/>
<entry endPc="268436910" name="j" stackId="4" startPc="268436776"/>
<entry endPc="268436910" name="ag" stackId="5" startPc="268436776"/>
<entry endPc="268436910" name="ip" stackId="6" startPc="268436776"/>
<entry arg="true" endPc="268436953" name="angle" stackId="1" startPc="268436911"/>
<entry arg="true" endPc="268436953" name="raidus" stackId="2" startPc="268436911"/>
<entry endPc="268436953" name="y" stackId="3" startPc="268436915"/>
<entry arg="true" endPc="268437034" name="dc" stackId="1" startPc="268436954"/>
<entry arg="true" endPc="268437034" name="percentage" stackId="2" startPc="268436954"/>
<entry arg="true" endPc="268437034" name="rad" stackId="3" startPc="268436954"/>
<entry arg="true" endPc="268437034" name="pen" stackId="4" startPc="268436954"/>
<entry arg="true" endPc="268437034" name="x" stackId="5" startPc="268436954"/>
<entry arg="true" endPc="268437034" name="y" stackId="6" startPc="268436954"/>
<entry endPc="268437033" name="endAngle" stackId="7" startPc="268436958"/>
<entry endPc="268437033" name="actualEndAngle" stackId="8" startPc="268436958"/>
<entry arg="true" endPc="268437051" name="val" stackId="1" startPc="268437035"/>
<entry arg="true" endPc="268437382" name="dc" stackId="1" startPc="268437052"/>
<entry arg="true" endPc="268437382" name="dd" stackId="2" startPc="268437052"/>
<entry arg="true" endPc="268437382" name="mm" stackId="3" startPc="268437052"/>
<entry arg="true" endPc="268437382" name="yy" stackId="4" startPc="268437052"/>
<entry arg="true" endPc="268437382" name="x" stackId="5" startPc="268437052"/>
<entry arg="true" endPc="268437382" name="y" stackId="6" startPc="268437052"/>
<entry endPc="268437381" name="A" stackId="7" startPc="268437056"/>
<entry endPc="268437381" name="w" stackId="8" startPc="268437056"/>
<entry endPc="268437381" name="F" stackId="9" startPc="268437056"/>
<entry endPc="268437381" name="Q" stackId="10" startPc="268437056"/>
<entry endPc="268437381" name="Q2" stackId="11" startPc="268437056"/>
<entry endPc="268437381" name="s" stackId="12" startPc="268437056"/>
<entry endPc="268437381" name="p" stackId="13" startPc="268437056"/>
<entry endPc="268437381" name="c" stackId="14" startPc="268437056"/>
<entry arg="true" endPc="268437463" name="dc" stackId="1" startPc="268437383"/>
<entry arg="true" endPc="268437463" name="percentage" stackId="2" startPc="268437383"/>
<entry arg="true" endPc="268437463" name="rad" stackId="3" startPc="268437383"/>
<entry arg="true" endPc="268437463" name="pen" stackId="4" startPc="268437383"/>
<entry arg="true" endPc="268437463" name="x" stackId="5" startPc="268437383"/>
<entry arg="true" endPc="268437463" name="y" stackId="6" startPc="268437383"/>
<entry endPc="268437462" name="endAngle" stackId="7" startPc="268437387"/>
<entry endPc="268437462" name="actualEndAngle" stackId="8" startPc="268437387"/>
<entry arg="true" endPc="268437506" name="angle" stackId="1" startPc="268437464"/>
<entry arg="true" endPc="268437506" name="raidus" stackId="2" startPc="268437464"/>
<entry endPc="268437506" name="x" stackId="3" startPc="268437468"/>
<entry arg="true" endPc="268437966" name="dc" stackId="1" startPc="268437507"/>
<entry arg="true" endPc="268438117" name="d" stackId="1" startPc="268437967"/>
<entry arg="true" endPc="268438117" name="m" stackId="2" startPc="268437967"/>
<entry arg="true" endPc="268438117" name="y" stackId="3" startPc="268437967"/>
<entry endPc="268438117" name="mm" stackId="4" startPc="268437971"/>
<entry endPc="268438117" name="yy" stackId="5" startPc="268437971"/>
<entry endPc="268438117" name="k1" stackId="6" startPc="268437971"/>
<entry endPc="268438117" name="k2" stackId="7" startPc="268437971"/>
<entry endPc="268438117" name="k3" stackId="8" startPc="268437971"/>
<entry endPc="268438117" name="j" stackId="9" startPc="268437971"/>
<entry arg="true" endPc="268439206" name="condition" stackId="1" startPc="268438118"/>
<entry arg="true" endPc="268440977" name="dc" stackId="1" startPc="268439228"/>
<entry endPc="268440976" name="clockTime" stackId="2" startPc="268439232"/>
<entry endPc="268440976" name="hourString" stackId="3" startPc="268439232"/>
<entry endPc="268440976" name="minuteString" stackId="4" startPc="268439232"/>
<entry endPc="268440976" name="info" stackId="5" startPc="268439232"/>
<entry endPc="268440976" name="steps" stackId="6" startPc="268439232"/>
<entry endPc="268440976" name="stepsGoal" stackId="7" startPc="268439232"/>
<entry endPc="268440976" name="floorsClimbed" stackId="8" startPc="268439232"/>
<entry endPc="268440976" name="floorsClimbedGoal" stackId="9" startPc="268439232"/>
<entry endPc="268440976" name="dateString" stackId="10" startPc="268439232"/>
<entry endPc="268440976" name="angle" stackId="11" startPc="268439232"/>
<entry endPc="268440976" name="x" stackId="12" startPc="268439232"/>
<entry endPc="268440976" name="y" stackId="13" startPc="268439232"/>
<entry endPc="268440976" name="hr" stackId="14" startPc="268439232"/>
<entry endPc="268440326" name="stepsProgress" stackId="15" startPc="268440249"/>
<entry endPc="268440411" name="floorsProgress" stackId="16" startPc="268440334"/>
<entry endPc="268440976" name="bb" stackId="17" startPc="268439232"/>
<entry endPc="268440897" name="feelLikeTemperature" stackId="18" startPc="268440644"/>
<entry arg="true" endPc="268440994" name="dc" stackId="1" startPc="268440978"/>
</localVars>
<annotations>
<annotationEntry annotation="initialized" class="Drawables" module="globals/Rez" symbol="LauncherIcon"/>
<annotationEntry annotation="initialized" class="Fonts" module="globals/Rez" symbol="t2"/>
<annotationEntry annotation="initialized" class="Drawables" module="globals/Rez" symbol="bgImage"/>
<annotationEntry annotation="initialized" class="Fonts" module="globals/Rez" symbol="t1"/>
<annotationEntry annotation="initialized" class="Fonts" module="globals/Rez" symbol="f2"/>
<annotationEntry annotation="initialized" class="Strings" module="globals/Rez" symbol="AppName"/>
<annotationEntry annotation="initialized" class="Fonts" module="globals/Rez" symbol="f1"/>
</annotations>
<dataEntryOffsetMappings>
<dataEntry label="globals" offset="87" parentId="" symbolId="globals" type="module"/>
<dataEntry label="globals/thirdfaceApp" offset="166" parentId="globals" symbolId="thirdfaceApp" type="class"/>
<dataEntry label="globals/thirdFaceDelegate" offset="237" parentId="globals" symbolId="thirdFaceDelegate" type="class"/>
<dataEntry label="globals/Rez" offset="292" parentId="globals" symbolId="Rez" type="module"/>
<dataEntry label="globals/thirdfaceView" offset="371" parentId="globals" symbolId="thirdfaceView" type="class"/>
<dataEntry label="globals/Rez/Drawables" offset="642" parentId="Rez" symbolId="Drawables" type="module"/>
<dataEntry label="globals/Rez/Layouts" offset="689" parentId="Rez" symbolId="Layouts" type="module"/>
<dataEntry label="globals/Rez/Menus" offset="728" parentId="Rez" symbolId="Menus" type="module"/>
<dataEntry label="globals/Rez/Fonts" offset="759" parentId="Rez" symbolId="Fonts" type="module"/>
<dataEntry label="globals/Rez/Strings" offset="822" parentId="Rez" symbolId="Strings" type="module"/>
<dataEntry label="globals/Rez/JsonData" offset="861" parentId="Rez" symbolId="JsonData" type="module"/>
</dataEntryOffsetMappings>
<functions>
<functionEntry accessMode="public" endPc="268435482" name="getApp" startPc="268435457">
<documentation/>
</functionEntry>
<functionEntry accessMode="public" endPc="268435501" name="&lt;init&gt;" parent="thirdfaceApp" startPc="268435483">
<documentation/>
</functionEntry>
<functionEntry accessMode="public" name="onStart" parent="thirdfaceApp">
<param id="state"/>
<documentation/>
</functionEntry>
<functionEntry accessMode="public" endPc="268435578" name="getInitialView" parent="thirdfaceApp" startPc="268435502">
<documentation/>
</functionEntry>
<functionEntry accessMode="public" endPc="268435599" name="initialize" parent="thirdfaceApp" startPc="268435579">
<documentation/>
</functionEntry>
<functionEntry accessMode="public" name="onStop" parent="thirdfaceApp">
<param id="state"/>
<documentation/>
</functionEntry>
<functionEntry accessMode="public" endPc="268435618" name="&lt;init&gt;" parent="thirdFaceDelegate" startPc="268435600">
<documentation/>
</functionEntry>
<functionEntry accessMode="public" endPc="268436707" name="onPress" parent="thirdFaceDelegate" startPc="268435619">
<param id="clickEvent"/>
<documentation/>
</functionEntry>
<functionEntry accessMode="public" endPc="268436728" name="initialize" parent="thirdFaceDelegate" startPc="268436708">
<documentation/>
</functionEntry>
<functionEntry accessMode="public" endPc="268436752" name="&lt;init&gt;" parent="Rez" startPc="268436729">
<documentation/>
</functionEntry>
<functionEntry accessMode="public" endPc="268436771" name="&lt;init&gt;" parent="thirdfaceView" startPc="268436753">
<documentation/>
</functionEntry>
<functionEntry accessMode="public" endPc="268436910" name="getMoonAge" parent="thirdfaceView" startPc="268436772">
<param id="d"/>
<param id="m"/>
<param id="y"/>
<documentation/>
</functionEntry>
<functionEntry accessMode="public" endPc="268436953" name="getYFromAngle" parent="thirdfaceView" startPc="268436911">
<param id="angle"/>
<param id="raidus"/>
<documentation/>
</functionEntry>
<functionEntry accessMode="public" endPc="268437034" name="drawProgressCCW" parent="thirdfaceView" startPc="268436954">
<param id="dc"/>
<param id="percentage"/>
<param id="rad"/>
<param id="pen"/>
<param id="x"/>
<param id="y"/>
<documentation/>
</functionEntry>
<functionEntry accessMode="public" endPc="268437051" name="getAngleFromTime" parent="thirdfaceView" startPc="268437035">
<param id="val"/>
<documentation/>
</functionEntry>
<functionEntry accessMode="public" endPc="268437382" name="drawMoon" parent="thirdfaceView" startPc="268437052">
<param id="dc"/>
<param id="dd"/>
<param id="mm"/>
<param id="yy"/>
<param id="x"/>
<param id="y"/>
<documentation/>
</functionEntry>
<functionEntry accessMode="public" name="onHide" parent="thirdfaceView">
<documentation/>
</functionEntry>
<functionEntry accessMode="public" endPc="268437463" name="drawProgressCW" parent="thirdfaceView" startPc="268437383">
<param id="dc"/>
<param id="percentage"/>
<param id="rad"/>
<param id="pen"/>
<param id="x"/>
<param id="y"/>
<documentation/>
</functionEntry>
<functionEntry accessMode="public" name="onExitSleep" parent="thirdfaceView">
<documentation/>
</functionEntry>
<functionEntry accessMode="public" endPc="268437506" name="getXFromAngle" parent="thirdfaceView" startPc="268437464">
<param id="angle"/>
<param id="raidus"/>
<documentation/>
</functionEntry>
<functionEntry accessMode="public" name="onShow" parent="thirdfaceView">
<documentation/>
</functionEntry>
<functionEntry accessMode="public" endPc="268437966" name="onLayout" parent="thirdfaceView" startPc="268437507">
<param id="dc"/>
<documentation/>
</functionEntry>
<functionEntry accessMode="public" endPc="268438117" name="getJulianDate" parent="thirdfaceView" startPc="268437967">
<param id="d"/>
<param id="m"/>
<param id="y"/>
<documentation/>
</functionEntry>
<functionEntry accessMode="public" endPc="268439206" name="getFriendlyCondition" parent="thirdfaceView" startPc="268438118">
<param id="condition"/>
<documentation/>
</functionEntry>
<functionEntry accessMode="public" name="onEnterSleep" parent="thirdfaceView">
<documentation/>
</functionEntry>
<functionEntry accessMode="public" endPc="268439227" name="initialize" parent="thirdfaceView" startPc="268439207">
<documentation/>
</functionEntry>
<functionEntry accessMode="public" endPc="268440977" name="onUpdate" parent="thirdfaceView" startPc="268439228">
<param id="dc"/>
<documentation/>
</functionEntry>
<functionEntry accessMode="public" name="&lt;init&gt;" parent="Drawables">
<documentation/>
</functionEntry>
<functionEntry accessMode="public" name="&lt;init&gt;" parent="Layouts">
<documentation/>
</functionEntry>
<functionEntry accessMode="public" name="&lt;init&gt;" parent="Menus">
<documentation/>
</functionEntry>
<functionEntry accessMode="public" name="&lt;init&gt;" parent="Fonts">
<documentation/>
</functionEntry>
<functionEntry accessMode="public" name="&lt;init&gt;" parent="Strings">
<documentation/>
</functionEntry>
<functionEntry accessMode="public" name="&lt;init&gt;" parent="JsonData">
<documentation/>
</functionEntry>
<functionEntry accessMode="public" endPc="268440994" name="WatchFace" parent="Layouts" startPc="268440978">
<param id="dc"/>
<documentation/>
</functionEntry>
</functions>
</debugInfo>
